langchain_s3_cached_embeddings/__init__.py
langchain_s3_cached_embeddings/embeddings/__init__.py
langchain_s3_cached_embeddings/embeddings/s3_cached_embeddings.py
langchain_s3_cached_embeddings-0.8.3.dist-info/LICENSE
langchain_s3_cached_embeddings-0.8.3.dist-info/METADATA
langchain_s3_cached_embeddings-0.8.3.dist-info/WHEEL
langchain_s3_cached_embeddings-0.8.3.dist-info/top_level.txt
langchain_s3_cached_embeddings-0.8.3.dist-info/RECORD
