Metadata-Version: 2.1
Name: langchain-s3-cached-embeddings
Version: 0.8.3
Summary: langchain embeddings wrapper to persist embeddings for re-use later
Author-email: Carmine DiMascio <cdimascio@gmail.com>
License: MIT
Requires-Python: >=3.11
License-File: LICENSE
Requires-Dist: boto3
Requires-Dist: langchain-core
